{
  "content": "Title: Pittsburgh Sightseeing Tours - Visit Pittsburgh | Visit Pittsburgh\nURL: https://www.visitpittsburgh.com/things-to-do/tours-sightseeing/\n\n\nNavigation\n----------\n\n📍 Strip District\n\nBurgh Bits & Bites Food Tour\n----------------------------\n\n\nTours & Sightseeing\n-------------------\n\n​However you like to roll, Pittsburgh is sure to have the sightseeing option for you.\nBy land or water, on four wheels or two, tour and experience Pittsburgh first hand.\nTag along with knowledgeable guides for free walking tours of Downtown, or take food tour to sample Pittsburgh's authentic culinary prowess. Get out on the water aboard the Gateway Clipper or the Rivers of Steel Riverboat. Keep active with a bike tour or keep it interesting on a Segway, there's something incredible to see in Pittsburgh, no matter how you get there.\nPlease enable JavaScript to show the Partner Listings listings.\n\nRelated Blog Posts\n------------------\n\nHow to Ride the Pittsburgh Inclines\nInclines, commonly known as Funiculars Railways, can be found all over the world and throughout history.\nTour the ​‘Burgh\nHere are a few unique ways to get a great sense of the city.\n6 Must-See Places in Pittsburgh\nAdd a visit these must-see places to your next Pittsburgh adventure!\nTop Free Things to Do in Pittsburgh\n​Who said you have to spend money to have a good time?\nPittsburgh Walking Tours\nWalk, tour, eat and explore\nMonuments, Memorials & Sculptures | A North Shore Walking Tour\nMonuments, memorials, sculptures and history along the river front\n\n25 Famous Pittsburgh Bridges\n----------------------------\n\n\nPlan Your Trip with the new Pittsburgh Insider's Guide\n------------------------------------------------------\n\n120 Fifth AvenueFifth Avenue PlaceSuite 2800Pittsburgh, PA 15222\n(412) 281-7711Toll Free: (877) 568-3744\n©️2025 Visit Pittsburgh. All Rights Reserved. Privacy Policy\nThis site uses cookies to enhance your experience.\n\nExperience Builder\n------------------\n\n\nQuick Search\n------------\n\n\nLocation Map\n------------\n",
  "metadata": {
    "source": "https://www.visitpittsburgh.com/things-to-do/tours-sightseeing/",
    "title": "Pittsburgh Sightseeing Tours - Visit Pittsburgh | Visit Pittsburgh",
    "category": "Pittsburgh",
    "subcategory": "Events",
    "date_scraped": "2025-03-11T16:46:46.925958",
    "depth": 5,
    "id": 6
  }
}